natural_reasoning/__init__.py
natural_reasoning-0.0.1.dist-info/LICENSE
natural_reasoning-0.0.1.dist-info/METADATA
natural_reasoning-0.0.1.dist-info/WHEEL
natural_reasoning-0.0.1.dist-info/top_level.txt
natural_reasoning-0.0.1.dist-info/RECORD
