Metadata-Version: 2.1
Name: natural-reasoning
Version: 0.0.1
Summary: Package description
Author-email: Alexander Fedotov <alex.fedotov@aol.com>
Project-URL: Homepage, https://github.com/natural-reasoning/natural-reasoning
Project-URL: Bug Tracker, https://github.com/natural-reasoning/natural-reasoning/issues
Classifier: Programming Language :: Python :: 3
Classifier: License :: OSI Approved :: MIT License
Classifier: Operating System :: OS Independent
Requires-Python: >=3.10
License-File: LICENSE
